[
  {
    "created_date": "2018-06-14 04:17:55",
    "current_time": 1528942675380,
    "in_reply_to_status_id_str": null,
    "in_reply_to_status_id": null,
    "created_at": "Thu Jun 14 02:17:55 +0000 2018",
    "in_reply_to_user_id_str": null,
    "source": "<a href=\"http://twitter.com/download/iphone\" rel=\"nofollow\">Twitter for iPhone</a>",
    "retweeted_status": {
      "extended_entities": {
        "media": [
          {
            "display_url": "pic.twitter.com/MoO10IHWTi",
            "indices": [
              112,
              135
            ],
            "sizes": {
              "small": {
                "w": 680,
                "h": 383,
                "resize": "fit"
              },
              "large": {
                "w": 1280,
                "h": 720,
                "resize": "fit"
              },
              "thumb": {
                "w": 150,
                "h": 150,
                "resize": "crop"
              },
              "medium": {
                "w": 1200,
                "h": 675,
                "resize": "fit"
              }
            },
            "id_str": "1006823579441344513",
            "expanded_url": "https://twitter.com/FIFAWorldCup/status/1006914097609404418/video/1",
            "media_url_https": "https://pbs.twimg.com/media/DfkJiDaX4AUbG9y.jpg",
            "id": 1006823579441344513,
            "additional_media_info": {
              "description": "",
              "title": "ONE DAY TO GO!",
              "embeddable": false,
              "monetizable": false
            },
            "type": "photo",
            "media_url": "http://pbs.twimg.com/media/DfkJiDaX4AUbG9y.jpg",
            "url": "https://t.co/MoO10IHWTi"
          }
        ]
      },
      "in_reply_to_status_id_str": null,
      "in_reply_to_status_id": null,
      "created_at": "Wed Jun 13 15:00:03 +0000 2018",
      "in_reply_to_user_id_str": null,
      "source": "<a href=\"https://ads.twitter.com\" rel=\"nofollow\">Twitter Ads</a>",
      "retweet_count": 3663,
      "retweeted": false,
      "geo": null,
      "filter_level": "low",
      "in_reply_to_screen_name": null,
      "is_quote_status": false,
      "id_str": "1006914097609404418",
      "in_reply_to_user_id": null,
      "favorite_count": 9337,
      "id": 1006914097609404418,
      "text": "The 2018 FIFA #WorldCup begins in exactly 24 hours time! \n\nReply with an emoji to express how excited you are 🙌 https://t.co/MoO10IHWTi",
      "place": null,
      "lang": "en",
      "quote_count": 596,
      "favorited": false,
      "possibly_sensitive": false,
      "coordinates": null,
      "truncated": false,
      "reply_count": 998,
      "entities": {
        "urls": [],
        "hashtags": [
          {
            "indices": [
              14,
              23
            ],
            "text": "WorldCup"
          }
        ],
        "media": [
          {
            "display_url": "pic.twitter.com/MoO10IHWTi",
            "indices": [
              112,
              135
            ],
            "sizes": {
              "small": {
                "w": 680,
                "h": 383,
                "resize": "fit"
              },
              "large": {
                "w": 1280,
                "h": 720,
                "resize": "fit"
              },
              "thumb": {
                "w": 150,
                "h": 150,
                "resize": "crop"
              },
              "medium": {
                "w": 1200,
                "h": 675,
                "resize": "fit"
              }
            },
            "id_str": "1006823579441344513",
            "expanded_url": "https://twitter.com/FIFAWorldCup/status/1006914097609404418/video/1",
            "media_url_https": "https://pbs.twimg.com/media/DfkJiDaX4AUbG9y.jpg",
            "id": 1006823579441344513,
            "additional_media_info": {
              "description": "",
              "title": "ONE DAY TO GO!",
              "embeddable": false,
              "monetizable": false
            },
            "type": "photo",
            "media_url": "http://pbs.twimg.com/media/DfkJiDaX4AUbG9y.jpg",
            "url": "https://t.co/MoO10IHWTi"
          }
        ],
        "user_mentions": [],
        "symbols": []
      },
      "display_text_range": [
        0,
        111
      ],
      "contributors": null,
      "user": {
        "utc_offset": null,
        "friends_count": 541,
        "profile_image_url_https": "https://pbs.twimg.com/profile_images/875621877279883264/sL6GBCf2_normal.jpg",
        "listed_count": 10913,
        "profile_background_image_url": "http://abs.twimg.com/images/themes/theme1/bg.png",
        "default_profile_image": false,
        "favourites_count": 322,
        "description": "The official Twitter account of the FIFA World Cup!",
        "created_at": "Thu Apr 29 10:58:07 +0000 2010",
        "is_translator": false,
        "profile_background_image_url_https": "https://abs.twimg.com/images/themes/theme1/bg.png",
        "protected": false,
        "screen_name": "FIFAWorldCup",
        "id_str": "138372303",
        "profile_link_color": "1F98C7",
        "translator_type": "none",
        "id": 138372303,
        "geo_enabled": true,
        "profile_background_color": "C6E2EE",
        "lang": "en",
        "profile_sidebar_border_color": "FFFFFF",
        "profile_text_color": "663B12",
        "verified": true,
        "profile_image_url": "http://pbs.twimg.com/profile_images/875621877279883264/sL6GBCf2_normal.jpg",
        "time_zone": null,
        "url": "http://www.fifa.com/worldcup",
        "contributors_enabled": false,
        "profile_background_tile": false,
        "profile_banner_url": "https://pbs.twimg.com/profile_banners/138372303/1438089096",
        "statuses_count": 15803,
        "follow_request_sent": null,
        "followers_count": 5957469,
        "profile_use_background_image": true,
        "default_profile": false,
        "following": null,
        "name": "FIFA World Cup 🏆",
        "location": null,
        "profile_sidebar_fill_color": "DAECF4",
        "notifications": null
      }
    },
    "retweet_count": 0,
    "retweeted": false,
    "geo": null,
    "filter_level": "low",
    "in_reply_to_screen_name": null,
    "is_quote_status": false,
    "id_str": "1007084688647839751",
    "in_reply_to_user_id": null,
    "favorite_count": 0,
    "id": 1007084688647839751,
    "text": "RT @FIFAWorldCup: The 2018 FIFA #WorldCup begins in exactly 24 hours time! \n\nReply with an emoji to express how excited you are 🙌 https://t…",
    "place": null,
    "lang": "en",
    "quote_count": 0,
    "favorited": false,
    "coordinates": null,
    "truncated": false,
    "timestamp_ms": "1528942675159",
    "reply_count": 0,
    "entities": {
      "urls": [],
      "hashtags": [
        {
          "indices": [
            32,
            41
          ],
          "text": "WorldCup"
        }
      ],
      "user_mentions": [
        {
          "indices": [
            3,
            16
          ],
          "screen_name": "FIFAWorldCup",
          "id_str": "138372303",
          "name": "FIFA World Cup 🏆",
          "id": 138372303
        }
      ],
      "symbols": []
    },
    "contributors": null,
    "user": {
      "utc_offset": null,
      "friends_count": 220,
      "profile_image_url_https": "https://pbs.twimg.com/profile_images/930072657768402944/CTK4oTeH_normal.jpg",
      "listed_count": 0,
      "profile_background_image_url": "http://abs.twimg.com/images/themes/theme9/bg.gif",
      "default_profile_image": false,
      "favourites_count": 94,
      "description": "Animal lover, vegetarian, loves yoga, philosophy, ethics and law. Never afraid to use my voice, power, or opinion. Be BOLD.",
      "created_at": "Wed Mar 02 23:40:00 +0000 2011",
      "is_translator": false,
      "profile_background_image_url_https": "https://abs.twimg.com/images/themes/theme9/bg.gif",
      "protected": false,
      "screen_name": "ShastaDeanna",
      "id_str": "259971568",
      "profile_link_color": "2FC2EF",
      "translator_type": "none",
      "id": 259971568,
      "geo_enabled": false,
      "profile_background_color": "1A1B1F",
      "lang": "en",
      "profile_sidebar_border_color": "181A1E",
      "profile_text_color": "666666",
      "verified": false,
      "profile_image_url": "http://pbs.twimg.com/profile_images/930072657768402944/CTK4oTeH_normal.jpg",
      "time_zone": null,
      "url": null,
      "contributors_enabled": false,
      "profile_background_tile": false,
      "profile_banner_url": "https://pbs.twimg.com/profile_banners/259971568/1429977737",
      "statuses_count": 285,
      "follow_request_sent": null,
      "followers_count": 44,
      "profile_use_background_image": true,
      "default_profile": false,
      "following": null,
      "name": "Shasta Deanna",
      "location": "London",
      "profile_sidebar_fill_color": "252429",
      "notifications": null
    }
  }
]