[
  {
    "created_date": "2018-06-15 20:42:44",
    "current_time": 1529088164882,
    "in_reply_to_status_id_str": null,
    "in_reply_to_status_id": null,
    "created_at": "Fri Jun 15 18:42:44 +0000 2018",
    "in_reply_to_user_id_str": null,
    "source": "<a href=\"http://twitter.com/download/android\" rel=\"nofollow\">Twitter for Android</a>",
    "retweeted_status": {
      "in_reply_to_status_id_str": null,
      "in_reply_to_status_id": null,
      "created_at": "Fri Jun 15 18:41:14 +0000 2018",
      "in_reply_to_user_id_str": null,
      "source": "<a href=\"http://twitter.com/download/iphone\" rel=\"nofollow\">Twitter for iPhone</a>",
      "retweet_count": 2,
      "retweeted": false,
      "geo": null,
      "filter_level": "low",
      "in_reply_to_screen_name": null,
      "is_quote_status": false,
      "id_str": "1007694535881777152",
      "in_reply_to_user_id": null,
      "favorite_count": 1,
      "id": 1007694535881777152,
      "text": "Pepe is joining hands, accepting his mistake...?\nChina, you broke him.\n#PORvESP #PORESP #Portugal #worldcup",
      "place": null,
      "lang": "en",
      "quote_count": 0,
      "favorited": false,
      "coordinates": null,
      "truncated": false,
      "reply_count": 0,
      "entities": {
        "urls": [],
        "hashtags": [
          {
            "indices": [
              71,
              79
            ],
            "text": "PORvESP"
          },
          {
            "indices": [
              80,
              87
            ],
            "text": "PORESP"
          },
          {
            "indices": [
              88,
              97
            ],
            "text": "Portugal"
          },
          {
            "indices": [
              98,
              107
            ],
            "text": "worldcup"
          }
        ],
        "user_mentions": [],
        "symbols": []
      },
      "contributors": null,
      "user": {
        "utc_offset": null,
        "friends_count": 70,
        "profile_image_url_https": "https://pbs.twimg.com/profile_images/1007351416271224832/T2Io38hx_normal.jpg",
        "listed_count": 3,
        "profile_background_image_url": "http://abs.twimg.com/images/themes/theme1/bg.png",
        "default_profile_image": false,
        "favourites_count": 12428,
        "description": "Become my friend and watch me go gaga over food, books, politics, animals and sports❤️😊P.s.: A very huge fan of Jersey no.7 (Dhoni and Ronaldo)",
        "created_at": "Tue Jan 13 22:33:48 +0000 2015",
        "is_translator": false,
        "profile_background_image_url_https": "https://abs.twimg.com/images/themes/theme1/bg.png",
        "protected": false,
        "screen_name": "iiiushiii",
        "id_str": "2980844258",
        "profile_link_color": "1DA1F2",
        "translator_type": "none",
        "id": 2980844258,
        "geo_enabled": true,
        "profile_background_color": "C0DEED",
        "lang": "en",
        "profile_sidebar_border_color": "C0DEED",
        "profile_text_color": "333333",
        "verified": false,
        "profile_image_url": "http://pbs.twimg.com/profile_images/1007351416271224832/T2Io38hx_normal.jpg",
        "time_zone": null,
        "url": "http://Instagram.com/ayushi____agarwal/",
        "contributors_enabled": false,
        "profile_background_tile": false,
        "profile_banner_url": "https://pbs.twimg.com/profile_banners/2980844258/1528922525",
        "statuses_count": 3302,
        "follow_request_sent": null,
        "followers_count": 361,
        "profile_use_background_image": true,
        "default_profile": true,
        "following": null,
        "name": "Ayushi Agarwal",
        "location": "मोह माया से दूर ",
        "profile_sidebar_fill_color": "DDEEF6",
        "notifications": null
      }
    },
    "retweet_count": 0,
    "retweeted": false,
    "geo": null,
    "filter_level": "low",
    "in_reply_to_screen_name": null,
    "is_quote_status": false,
    "id_str": "1007694915638198272",
    "in_reply_to_user_id": null,
    "favorite_count": 0,
    "id": 1007694915638198272,
    "text": "RT @iiiushiii: Pepe is joining hands, accepting his mistake...?\nChina, you broke him.\n#PORvESP #PORESP #Portugal #worldcup",
    "place": null,
    "lang": "en",
    "quote_count": 0,
    "favorited": false,
    "coordinates": null,
    "truncated": false,
    "timestamp_ms": "1529088164611",
    "reply_count": 0,
    "entities": {
      "urls": [],
      "hashtags": [
        {
          "indices": [
            86,
            94
          ],
          "text": "PORvESP"
        },
        {
          "indices": [
            95,
            102
          ],
          "text": "PORESP"
        },
        {
          "indices": [
            103,
            112
          ],
          "text": "Portugal"
        },
        {
          "indices": [
            113,
            122
          ],
          "text": "worldcup"
        }
      ],
      "user_mentions": [
        {
          "indices": [
            3,
            13
          ],
          "screen_name": "iiiushiii",
          "id_str": "2980844258",
          "name": "Ayushi Agarwal",
          "id": 2980844258
        }
      ],
      "symbols": []
    },
    "contributors": null,
    "user": {
      "utc_offset": null,
      "friends_count": 3105,
      "profile_image_url_https": "https://pbs.twimg.com/profile_images/981813850763755520/WY2HMDpH_normal.jpg",
      "listed_count": 83,
      "profile_background_image_url": "http://abs.twimg.com/images/themes/theme18/bg.gif",
      "default_profile_image": false,
      "favourites_count": 9200,
      "description": "【 ALone SuRvIvor in This wOrlD 】\n\n                  \n               Follow = Follow , \n\n🔃 FoLloW bAcK 🔃 #BulletRetweeter \n\n Follow must",
      "created_at": "Mon Feb 16 07:52:02 +0000 2015",
      "is_translator": false,
      "profile_background_image_url_https": "https://abs.twimg.com/images/themes/theme18/bg.gif",
      "protected": false,
      "screen_name": "Im_TheWall",
      "id_str": "3022072122",
      "profile_link_color": "FF691F",
      "translator_type": "none",
      "id": 3022072122,
      "geo_enabled": false,
      "profile_background_color": "000000",
      "lang": "en",
      "profile_sidebar_border_color": "000000",
      "profile_text_color": "000000",
      "verified": false,
      "profile_image_url": "http://pbs.twimg.com/profile_images/981813850763755520/WY2HMDpH_normal.jpg",
      "time_zone": null,
      "url": "http://dhavalmendapara.wordpress.com",
      "contributors_enabled": false,
      "profile_background_tile": false,
      "profile_banner_url": "https://pbs.twimg.com/profile_banners/3022072122/1460181287",
      "statuses_count": 208584,
      "follow_request_sent": null,
      "followers_count": 6219,
      "profile_use_background_image": false,
      "default_profile": false,
      "following": null,
      "name": "♥The wall♥ Football",
      "location": "in someone's thought",
      "profile_sidebar_fill_color": "000000",
      "notifications": null
    }
  },
  {
    "created_date": "2018-06-15 20:44:46",
    "current_time": 1529088286051,
    "in_reply_to_status_id_str": null,
    "in_reply_to_status_id": null,
    "created_at": "Fri Jun 15 18:44:45 +0000 2018",
    "in_reply_to_user_id_str": null,
    "source": "<a href=\"http://twitter.com/download/android\" rel=\"nofollow\">Twitter for Android</a>",
    "retweeted_status": {
      "extended_tweet": {
        "entities": {
          "urls": [],
          "hashtags": [
            {
              "indices": [
                229,
                238
              ],
              "text": "WorldCup"
            }
          ],
          "user_mentions": [],
          "symbols": []
        },
        "full_text": "If you have less than 79k followers \n\nRetweet now\nRetweet now\n\nFollow retweet list in bits 50 at a time\nFollow back instantly, reply \"ifb\"\n\nAfter 10 minutes,Undo retweet &amp; retweet again,it works!!!\n\n450+ followers guaranteed\n#WorldCup\nLet’s Prosper Together\n🔥⏰⏰🔥",
        "display_text_range": [
          0,
          266
        ]
      },
      "in_reply_to_status_id_str": null,
      "in_reply_to_status_id": null,
      "created_at": "Fri Jun 15 17:00:11 +0000 2018",
      "in_reply_to_user_id_str": null,
      "source": "<a href=\"http://www.crowdfireapp.com\" rel=\"nofollow\">Crowdfire - Go Big</a>",
      "retweet_count": 377,
      "retweeted": false,
      "geo": null,
      "filter_level": "low",
      "in_reply_to_screen_name": null,
      "is_quote_status": false,
      "id_str": "1007669107918016512",
      "in_reply_to_user_id": null,
      "favorite_count": 543,
      "id": 1007669107918016512,
      "text": "If you have less than 79k followers \n\nRetweet now\nRetweet now\n\nFollow retweet list in bits 50 at a time\nFollow back… https://t.co/WwprKsSyTs",
      "place": null,
      "lang": "en",
      "quote_count": 0,
      "favorited": false,
      "coordinates": null,
      "truncated": true,
      "reply_count": 72,
      "entities": {
        "urls": [
          {
            "display_url": "twitter.com/i/web/status/1…",
            "indices": [
              117,
              140
            ],
            "expanded_url": "https://twitter.com/i/web/status/1007669107918016512",
            "url": "https://t.co/WwprKsSyTs"
          }
        ],
        "hashtags": [],
        "user_mentions": [],
        "symbols": []
      },
      "contributors": null,
      "user": {
        "utc_offset": null,
        "friends_count": 11679,
        "profile_image_url_https": "https://pbs.twimg.com/profile_images/996756859745906688/yCNtEe9n_normal.jpg",
        "listed_count": 37,
        "profile_background_image_url": "",
        "default_profile_image": false,
        "favourites_count": 2522,
        "description": "||#SuperVars|| Join the movement let's grow together || GainPage",
        "created_at": "Thu Feb 02 10:47:33 +0000 2017",
        "is_translator": false,
        "profile_background_image_url_https": "",
        "protected": false,
        "screen_name": "VarsColIen",
        "id_str": "827106172331241472",
        "profile_link_color": "1DA1F2",
        "translator_type": "none",
        "id": 827106172331241472,
        "geo_enabled": false,
        "profile_background_color": "F5F8FA",
        "lang": "en",
        "profile_sidebar_border_color": "C0DEED",
        "profile_text_color": "333333",
        "verified": false,
        "profile_image_url": "http://pbs.twimg.com/profile_images/996756859745906688/yCNtEe9n_normal.jpg",
        "time_zone": null,
        "url": null,
        "contributors_enabled": false,
        "profile_background_tile": false,
        "profile_banner_url": "https://pbs.twimg.com/profile_banners/827106172331241472/1526480326",
        "statuses_count": 1758,
        "follow_request_sent": null,
        "followers_count": 12970,
        "profile_use_background_image": true,
        "default_profile": true,
        "following": null,
        "name": "vars_d'frens",
        "location": "TurnOn Notifications ",
        "profile_sidebar_fill_color": "DDEEF6",
        "notifications": null
      }
    },
    "retweet_count": 0,
    "retweeted": false,
    "geo": null,
    "filter_level": "low",
    "in_reply_to_screen_name": null,
    "is_quote_status": false,
    "id_str": "1007695423950151681",
    "in_reply_to_user_id": null,
    "favorite_count": 0,
    "id": 1007695423950151681,
    "text": "RT @VarsColIen: If you have less than 79k followers \n\nRetweet now\nRetweet now\n\nFollow retweet list in bits 50 at a time\nFollow back instant…",
    "place": null,
    "lang": "en",
    "quote_count": 0,
    "favorited": false,
    "coordinates": null,
    "truncated": false,
    "timestamp_ms": "1529088285802",
    "reply_count": 0,
    "entities": {
      "urls": [],
      "hashtags": [],
      "user_mentions": [
        {
          "indices": [
            3,
            14
          ],
          "screen_name": "VarsColIen",
          "id_str": "827106172331241472",
          "name": "vars_d'frens",
          "id": 827106172331241472
        }
      ],
      "symbols": []
    },
    "contributors": null,
    "user": {
      "utc_offset": null,
      "friends_count": 3105,
      "profile_image_url_https": "https://pbs.twimg.com/profile_images/981813850763755520/WY2HMDpH_normal.jpg",
      "listed_count": 83,
      "profile_background_image_url": "http://abs.twimg.com/images/themes/theme18/bg.gif",
      "default_profile_image": false,
      "favourites_count": 9200,
      "description": "【 ALone SuRvIvor in This wOrlD 】\n\n                  \n               Follow = Follow , \n\n🔃 FoLloW bAcK 🔃 #BulletRetweeter \n\n Follow must",
      "created_at": "Mon Feb 16 07:52:02 +0000 2015",
      "is_translator": false,
      "profile_background_image_url_https": "https://abs.twimg.com/images/themes/theme18/bg.gif",
      "protected": false,
      "screen_name": "Im_TheWall",
      "id_str": "3022072122",
      "profile_link_color": "FF691F",
      "translator_type": "none",
      "id": 3022072122,
      "geo_enabled": false,
      "profile_background_color": "000000",
      "lang": "en",
      "profile_sidebar_border_color": "000000",
      "profile_text_color": "000000",
      "verified": false,
      "profile_image_url": "http://pbs.twimg.com/profile_images/981813850763755520/WY2HMDpH_normal.jpg",
      "time_zone": null,
      "url": "http://dhavalmendapara.wordpress.com",
      "contributors_enabled": false,
      "profile_background_tile": false,
      "profile_banner_url": "https://pbs.twimg.com/profile_banners/3022072122/1460181287",
      "statuses_count": 208588,
      "follow_request_sent": null,
      "followers_count": 6222,
      "profile_use_background_image": false,
      "default_profile": false,
      "following": null,
      "name": "♥The wall♥ Football",
      "location": "in someone's thought",
      "profile_sidebar_fill_color": "000000",
      "notifications": null
    }
  }
]